{
  "name": "Artisan's Intuition",
  "type": "feat",
  "system": {
    "description": {
      "value": "",
      "chat": ""
    },
    "source": {
      "custom": "Eberron: Rising from the Last War",
      "revision": 1,
      "rules": "2014"
    },
    "uses": {
      "max": "",
      "spent": 0,
      "recovery": []
    },
    "type": {
      "value": "race",
      "subtype": ""
    },
    "requirements": "",
    "properties": [],
    "prerequisites": {
      "level": null
    },
    "activities": {},
    "identifier": "artisans-intuition",
    "enchant": {}
  },
  "flags": {
    "chris-premades": {
      "info": {
        "name": "Artisan's Intuition",
        "version": "1.1.0",
        "identifier": "artisansIntuition",
        "source": "chris-premades"
      }
    },
    "midiProperties": {
      "confirmTargets": "default",
      "autoFailFriendly": false,
      "autoSaveFriendly": false,
      "critOther": false,
      "offHandWeapon": false,
      "magicdam": false,
      "magiceffect": false,
      "noConcentrationCheck": false,
      "toggleEffect": false,
      "ignoreTotalCover": false,
      "idr": false,
      "idi": false,
      "idv": false,
      "ida": false
    },
    "midi-qol": {
      "rollAttackPerTarget": "default",
      "itemCondition": "",
      "effectCondition": "",
      "AoETargetType": "any",
      "AoETargetTypeIncludeSelf": true,
      "autoTarget": "default",
      "removeAttackDamageButtons": "default",
      "reactionCondition": "",
      "otherCondition": ""
    },
    "dnd5e": {
      "riders": {
        "activity": []
      }
    }
  },
  "effects": [
    {
      "name": "Artisan's Intuition",
      "origin": "Compendium.world.cpr-race-features.Item.PFps4HYyiTrnpVav",
      "duration": {
        "rounds": null,
        "startTime": 1488,
        "seconds": null,
        "combat": null,
        "turns": null,
        "startRound": 249,
        "startTurn": 0
      },
      "disabled": false,
      "flags": {
        "dnd5e": {},
        "dae": {
          "disableCondition": "",
          "disableIncapacitated": false,
          "stackable": "noneName",
          "showIcon": false,
          "durationExpression": "",
          "macroRepeat": "none",
          "specialDuration": []
        },
        "core": {
          "overlay": false
        }
      },
      "img": "icons/tools/hand/hammer-and-nail.webp",
      "_id": "FuaHgyI3N2qJ3bXz",
      "type": "base",
      "system": {},
      "changes": [
        {
          "key": "system.skills.arc.bonuses.check",
          "mode": 2,
          "value": "1d4",
          "priority": 20
        },
        {
          "key": "system.tools.art.bonuses.check",
          "mode": 2,
          "value": "1d4",
          "priority": 20
        }
      ],
      "description": "",
      "tint": "#ffffff",
      "transfer": true,
      "statuses": [],
      "sort": 0,
      "_stats": {
        "compendiumSource": null,
        "duplicateSource": null,
        "coreVersion": "12.343",
        "systemId": "dnd5e",
        "systemVersion": "4.1.2",
        "createdTime": null,
        "modifiedTime": null,
        "lastModifiedBy": null
      },
      "_key": "!items.effects!9Eoc1pt5hGTMwKxa.FuaHgyI3N2qJ3bXz"
    }
  ],
  "img": "icons/tools/hand/hammer-and-nail.webp",
  "folder": "Ykr1ykVDNkhDALu8",
  "_id": "9Eoc1pt5hGTMwKxa",
  "_key": "!items!9Eoc1pt5hGTMwKxa"
}
