{
  "name": "Evasion",
  "type": "feat",
  "system": {
    "description": {
      "value": "",
      "chat": ""
    },
    "source": {
      "custom": "Rogue",
      "revision": 1,
      "rules": "2014"
    },
    "uses": {
      "max": "",
      "spent": 0,
      "recovery": []
    },
    "type": {
      "value": "class",
      "subtype": ""
    },
    "requirements": "",
    "properties": [],
    "prerequisites": {
      "level": null
    },
    "activities": {},
    "identifier": "evasion",
    "enchant": {}
  },
  "flags": {
    "midi-qol": {
      "onUseMacroName": "",
      "rollAttackPerTarget": "default",
      "itemCondition": "",
      "effectCondition": "",
      "AoETargetType": "any",
      "AoETargetTypeIncludeSelf": true,
      "autoTarget": "default",
      "removeAttackDamageButtons": "default",
      "reactionCondition": "",
      "otherCondition": ""
    },
    "midiProperties": {
      "confirmTargets": "default",
      "autoFailFriendly": false,
      "autoSaveFriendly": false,
      "critOther": false,
      "offHandWeapon": false,
      "magicdam": false,
      "magiceffect": false,
      "noConcentrationCheck": false,
      "toggleEffect": false,
      "ignoreTotalCover": false,
      "idr": false,
      "idi": false,
      "idv": false,
      "ida": false
    },
    "core": {},
    "dnd5e": {
      "riders": {
        "activity": []
      }
    },
    "chris-premades": {
      "info": {
        "name": "Evasion",
        "version": "1.1.0",
        "identifier": "evasion",
        "source": "chris-premades"
      }
    }
  },
  "effects": [
    {
      "name": "Evasion",
      "origin": "Compendium.world.cpr-class-features.Item.wrJMIAyqHD1YzK8w",
      "duration": {
        "rounds": null,
        "startTime": 1404,
        "seconds": null,
        "combat": null,
        "turns": null,
        "startRound": 235,
        "startTurn": 8
      },
      "disabled": false,
      "flags": {
        "dnd5e": {},
        "dae": {
          "disableCondition": "",
          "disableIncapacitated": false,
          "stackable": "noneName",
          "showIcon": false,
          "durationExpression": "",
          "macroRepeat": "none",
          "specialDuration": []
        },
        "core": {
          "overlay": false
        }
      },
      "img": "icons/magic/light/beam-red-orange.webp",
      "_id": "bzHUnvkGjSExvEfB",
      "type": "base",
      "system": {},
      "changes": [
        {
          "key": "flags.midi-qol.superSaver.dex",
          "mode": 5,
          "value": "1",
          "priority": 20
        }
      ],
      "description": "",
      "tint": "#ffffff",
      "transfer": true,
      "statuses": [],
      "sort": 0,
      "_stats": {
        "compendiumSource": null,
        "duplicateSource": null,
        "coreVersion": "12.331",
        "systemId": "dnd5e",
        "systemVersion": "4.1.2",
        "createdTime": null,
        "modifiedTime": null,
        "lastModifiedBy": null
      },
      "_key": "!items.effects!0Jr1itXw0XXBazgt.bzHUnvkGjSExvEfB"
    }
  ],
  "img": "icons/magic/light/beam-red-orange.webp",
  "folder": "otD6Ysu1O9jlyA49",
  "_id": "0Jr1itXw0XXBazgt",
  "_key": "!items!0Jr1itXw0XXBazgt"
}
