{
  "name": "Eye for Weakness",
  "type": "feat",
  "system": {
    "description": {
      "value": "",
      "chat": ""
    },
    "source": {
      "custom": "Rogue : Inquisitive",
      "revision": 1,
      "rules": "2014"
    },
    "uses": {
      "max": "",
      "spent": 0,
      "recovery": []
    },
    "type": {
      "value": "class",
      "subtype": ""
    },
    "requirements": "",
    "properties": [],
    "prerequisites": {
      "level": null
    },
    "activities": {},
    "identifier": "eye-for-weakness",
    "enchant": {}
  },
  "flags": {
    "core": {},
    "midiProperties": {
      "confirmTargets": "default",
      "autoFailFriendly": false,
      "autoSaveFriendly": false,
      "critOther": false,
      "offHandWeapon": false,
      "magicdam": false,
      "magiceffect": false,
      "noConcentrationCheck": false,
      "toggleEffect": false,
      "ignoreTotalCover": false,
      "idr": false,
      "idi": false,
      "idv": false,
      "ida": false
    },
    "midi-qol": {
      "rollAttackPerTarget": "default",
      "itemCondition": "",
      "effectCondition": "",
      "AoETargetType": "any",
      "AoETargetTypeIncludeSelf": true,
      "autoTarget": "default",
      "removeAttackDamageButtons": "default",
      "reactionCondition": "",
      "otherCondition": ""
    },
    "dnd5e": {
      "riders": {
        "activity": []
      }
    },
    "chris-premades": {
      "info": {
        "name": "Eye for Weakness",
        "version": "1.1.0",
        "identifier": "eyeForWeakness",
        "source": "chris-premades"
      }
    }
  },
  "effects": [],
  "img": "icons/magic/perception/eye-ringed-glow-angry-red.webp",
  "folder": "cZ9H14zCRzQkMq34",
  "_id": "JShMVTAGa1zTNi5D",
  "_key": "!items!JShMVTAGa1zTNi5D"
}
